.gitignore
LICENSE
README.md
logo0.png
setup.py
terminedia_paint/__init__.py
terminedia_paint/__main__.py
terminedia_paint.egg-info/PKG-INFO
terminedia_paint.egg-info/SOURCES.txt
terminedia_paint.egg-info/dependency_links.txt
terminedia_paint.egg-info/entry_points.txt
terminedia_paint.egg-info/requires.txt
terminedia_paint.egg-info/top_level.txt
terminedia_paint.egg-info/zip-safe