Metadata-Version: 2.1
Name: terminedia-paint
Version: 0.1.0
Summary: Applicative to draw images interactively on the posix terminal
Home-page: https://github.com/jsbueno/terminedia-paint
Author: João S. O. Bueno
Author-email: gwidion@gmail.com
License: LGPLv3+
Project-URL: Source Code, https://github.com/jsbueno/terminedia-paint
Keywords: terminal cmd posix xterm ANSI color
Platform: UNKNOWN
Classifier: Development Status :: 4 - Beta
Classifier: Intended Audience :: Developers
Classifier: Intended Audience :: System Administrators
Classifier: Programming Language :: Python :: 3
Classifier: Programming Language :: Python :: 3.6
Classifier: Programming Language :: Python :: 3.7
Classifier: Programming Language :: Python :: 3.8
Classifier: Programming Language :: Python :: 3.9
Classifier: Programming Language :: Python :: 3.10
Classifier: Programming Language :: Python :: Implementation :: PyPy
Classifier: License :: OSI Approved :: GNU Lesser General Public License v3 or later (LGPLv3+)
Classifier: License :: OSI Approved :: GNU General Public License v3 or later (GPLv3+)
Classifier: Operating System :: OS Independent
Classifier: Topic :: Artistic Software
Classifier: Topic :: Multimedia :: Graphics
Classifier: Topic :: Terminals
Classifier: Topic :: Terminals :: Terminal Emulators/X Terminals
Provides-Extra: images
Provides-Extra: tests
